HISTORY.rst
LICENSE
MANIFEST.in
README.rst
setup.cfg
setup.py
python_traceview.egg-info/PKG-INFO
python_traceview.egg-info/SOURCES.txt
python_traceview.egg-info/dependency_links.txt
python_traceview.egg-info/requires.txt
python_traceview.egg-info/top_level.txt
traceview/__init__.py
traceview/annotation.py
traceview/api.py
traceview/app.py
traceview/discovery.py
traceview/error.py
traceview/formatters.py
traceview/host.py
traceview/latency.py
traceview/organization.py
traceview/resource.py
traceview/total_request.py