Metadata-Version: 1.1
Name: python-traceview
Version: 0.7.0
Summary: TraceView API Client
Home-page: https://github.com/danriti/python-traceview
Author: Daniel Riti
Author-email: dmriti@gmail.com
License: MIT
Keywords: traceview api client development performance
Platform: UNKNOWN
Classifier: Development Status :: 4 - Beta
Classifier: Intended Audience :: Developers
Classifier: License :: OSI Approved :: MIT License
Classifier: Programming Language :: Python :: 2
Classifier: Programming Language :: Python :: 2.7
Classifier: Programming Language :: Python :: 3
Classifier: Programming Language :: Python :: 3.3
Classifier: Programming Language :: Python :: 3.4
Classifier: Programming Language :: Python :: 3.5
